pytest_postgresql/__init__.py
pytest_postgresql/config.py
pytest_postgresql/exceptions.py
pytest_postgresql/executor.py
pytest_postgresql/executor_noop.py
pytest_postgresql/janitor.py
pytest_postgresql/loader.py
pytest_postgresql/plugin.py
pytest_postgresql/py.typed
pytest_postgresql/retry.py
pytest_postgresql/factories/__init__.py
pytest_postgresql/factories/client.py
pytest_postgresql/factories/noprocess.py
pytest_postgresql/factories/process.py
pytest_postgresql-7.0.2.dist-info/licenses/AUTHORS.rst
pytest_postgresql-7.0.2.dist-info/licenses/COPYING
pytest_postgresql-7.0.2.dist-info/licenses/COPYING.lesser
pytest_postgresql-7.0.2.dist-info/METADATA
pytest_postgresql-7.0.2.dist-info/WHEEL
pytest_postgresql-7.0.2.dist-info/entry_points.txt
pytest_postgresql-7.0.2.dist-info/top_level.txt
pytest_postgresql-7.0.2.dist-info/zip-safe
pytest_postgresql-7.0.2.dist-info/RECORD
