Metadata-Version: 2.4
Name: pytest-postgresql
Version: 7.0.2
Summary: Postgresql fixtures and fixture factories for Pytest.
Author-email: Grzegorz Śliwiński <fizyk+pypi@fizyk.dev>
Project-URL: Source, https://github.com/dbfixtures/pytest-postgresql
Project-URL: Bug Tracker, https://github.com/dbfixtures/pytest-postgresql/issues
Project-URL: Changelog, https://github.com/dbfixtures/pytest-postgresql/blob/v7.0.2/CHANGES.rst
Keywords: tests,pytest,fixture,postgresql
Classifier: Development Status :: 5 - Production/Stable
Classifier: Environment :: Web Environment
Classifier: Intended Audience :: Developers
Classifier: License :: OSI Approved :: GNU Lesser General Public License v3 or later (LGPLv3+)
Classifier: Natural Language :: English
Classifier: Operating System :: OS Independent
Classifier: Programming Language :: Python
Classifier: Programming Language :: Python :: 3
Classifier: Programming Language :: Python :: 3.9
Classifier: Programming Language :: Python :: 3.10
Classifier: Programming Language :: Python :: 3.11
Classifier: Programming Language :: Python :: 3.12
Classifier: Programming Language :: Python :: 3.13
Classifier: Programming Language :: Python :: 3 :: Only
Classifier: Topic :: Software Development :: Libraries :: Python Modules
Classifier: Topic :: Software Development :: Testing
Classifier: Framework :: Pytest
Requires-Python: >=3.9
License-File: COPYING
License-File: COPYING.lesser
License-File: AUTHORS.rst
Requires-Dist: pytest>=7.2
Requires-Dist: port-for>=0.7.3
Requires-Dist: mirakuru>=2.6.0
Requires-Dist: packaging
Requires-Dist: psycopg>=3.0.0
Dynamic: license-file
